LICENSE
MANIFEST.in
README.md
setup.py
songkiss/__init__.py
songkiss/api_helper.py
songkiss/configuration.py
songkiss/decorators.py
songkiss/songkiss_client.py
songkiss.egg-info/PKG-INFO
songkiss.egg-info/SOURCES.txt
songkiss.egg-info/dependency_links.txt
songkiss.egg-info/requires.txt
songkiss.egg-info/top_level.txt
songkiss/controllers/__init__.py
songkiss/controllers/artists_controller.py
songkiss/controllers/base_controller.py
songkiss/controllers/search_controller.py
songkiss/exceptions/__init__.py
songkiss/exceptions/api_exception.py
songkiss/http/__init__.py
songkiss/http/http_call_back.py
songkiss/http/http_client.py
songkiss/http/http_context.py
songkiss/http/http_method_enum.py
songkiss/http/http_request.py
songkiss/http/http_response.py
songkiss/http/requests_client.py
songkiss/http/auth/__init__.py
songkiss/http/auth/custom_query_auth.py
songkiss/models/__init__.py
songkiss/models/artist.py
songkiss/models/artist_1.py
songkiss/models/country.py
songkiss/models/event.py
songkiss/models/get_artist_calendar_response.py
songkiss/models/get_search_artists_response.py
songkiss/models/get_similar_artists_response.py
songkiss/models/identifier.py
songkiss/models/identifier_1.py
songkiss/models/location.py
songkiss/models/metro_area.py
songkiss/models/performance.py
songkiss/models/results.py
songkiss/models/results_1.py
songkiss/models/results_page.py
songkiss/models/results_page_1.py
songkiss/models/start.py
songkiss/models/venue.py