Metadata-Version: 1.0
Name: songkiss
Version: 0.1
Summary: SongKick API for GigBot usage
Home-page: https://stoplight.io
Author: Stoplight
Author-email: support@apimatic.io
License: UNKNOWN
Platform: UNKNOWN
